Metadata-Version: 1.0
Name: hogwarts
Version: 0.0.4
Summary: Framework for writing/running text adventure games
Home-page: http://github.com/astrosilverio/hogwarts
Author: astrosilverio
Author-email: astrosilverio@gmail.com
License: MIT
Platform: UNKNOWN
